pyrasp/__init__.py
pyrasp/pyrasp.py
pyrasp/pyrasp_data.py
pyrasp/pyrasp_gpt.py
pyrasp/data/prompt_model-1.0.0
pyrasp/data/sqli_model-3.1.0
pyrasp/data/xss_model-3.1.0
pyrasp-0.9.2.dist-info/licenses/LICENSE
pyrasp-0.9.2.dist-info/METADATA
pyrasp-0.9.2.dist-info/WHEEL
pyrasp-0.9.2.dist-info/top_level.txt
pyrasp-0.9.2.dist-info/RECORD
