Metadata-Version: 2.4
Name: pyrasp
Version: 0.9.2
Summary: Python RASP
Author-email: Renaud Bidou <renaud@paracyberbellum.io>
License: Attribution-NonCommercial-ShareAlike 4.0 International
Project-URL: Homepage, https://pyrasp.paracyberbellum.io
Project-URL: Documentation, https://paracyberbellum.gitbook.io/pyrasp
Project-URL: GitHub, https://github.com/rbidou/pyrasp
Keywords: rasp,web application,security,xss,sql injection,waf,dlp,mcp,llm,prompt injection,ai,machine learning
Classifier: Development Status :: 4 - Beta
Classifier: Programming Language :: Python
Classifier: Framework :: Flask
Classifier: Framework :: Django
Classifier: Framework :: FastAPI
Requires-Python: >=3.7
License-File: LICENSE
Requires-Dist: scikit-learn==1.6.0
Requires-Dist: numpy==1.*
Requires-Dist: requests>=2.32.2
Requires-Dist: psutil>=6.0.0
Requires-Dist: pyjwt==2.8.0
Requires-Dist: cloudpickle==3.1.0
Requires-Dist: setuptools>=78.1.1
Requires-Dist: loguru
Requires-Dist: fastmcp
Requires-Dist: importlib_resources
Requires-Dist: torch==2.9.*
Requires-Dist: tiktoken==0.12.0
Dynamic: license-file
